icp_lattice_calculator-0.1.1.dist-info/licenses/LICENSE
lattice_calculator/__init__.py
lattice_calculator/lattice_calculator.py
icp_lattice_calculator-0.1.1.dist-info/METADATA
icp_lattice_calculator-0.1.1.dist-info/WHEEL
icp_lattice_calculator-0.1.1.dist-info/top_level.txt
icp_lattice_calculator-0.1.1.dist-info/RECORD
