Metadata-Version: 2.4
Name: icp-lattice-calculator
Version: 0.1.1
Summary: Crystallographic lattice calculations and instrument angle transformations
Author-email: Your Name <your.email@example.com>
License: MIT
Project-URL: Homepage, https://github.com/yourusername/icp-lattice-calculator
Project-URL: Bug Tracker, https://github.com/yourusername/icp-lattice-calculator/issues
Project-URL: Documentation, https://github.com/yourusername/icp-lattice-calculator#readme
Keywords: crystallography,neutron scattering,lattice,triple axis
Classifier: Development Status :: 4 - Beta
Classifier: Intended Audience :: Science/Research
Classifier: License :: OSI Approved :: MIT License
Classifier: Programming Language :: Python :: 3
Classifier: Programming Language :: Python :: 3.7
Classifier: Programming Language :: Python :: 3.8
Classifier: Programming Language :: Python :: 3.9
Classifier: Programming Language :: Python :: 3.10
Classifier: Topic :: Scientific/Engineering :: Physics
Classifier: Topic :: Scientific/Engineering :: Chemistry
Classifier: Topic :: Scientific/Engineering :: Visualization
Requires-Python: >=3.7
License-File: LICENSE
Requires-Dist: numpy>=1.17.0
Provides-Extra: dev
Requires-Dist: pytest>=6.0.0; extra == "dev"
Requires-Dist: pytest-cov>=2.12.0; extra == "dev"
Requires-Dist: black>=21.5b2; extra == "dev"
Requires-Dist: isort>=5.9.1; extra == "dev"
Requires-Dist: flake8>=3.9.2; extra == "dev"
Dynamic: license-file
